{
    "2": "light.kitchen",
    "3": "script.dinner",
    "5": "light.nightstand_1",
    "6": "media_player.shield",
    "7": "switch.humidifier",
    "9": "light.tree_lamp_5",
    "10": "light.tree_lamp_3",
    "11": "light.tree_lamp_4",
    "12": "group.all_lights",
    "14": "switch.xbox_360",
    "15": "light.living_room_lamp_1",
    "16": "light.tree_lamp_2",
    "17": "scene.tv_dinner",
    "19": "switch.christmas_tree",
    "21": "light.dining_lights_level",
    "22": "switch.shield_audio",
    "24": "switch.projector",
    "25": "scene.romantic",
    "26": "switch.apartment_fan",
    "27": "switch.plex",
    "28": "light.tree_lamp_1",
    "29": "script.bedtime",
    "31": "scene.up_late",
    "32": "switch.xbox_one",
    "33": "light.living_room_lamp_2",
    "42": "script.lights_out",
    "43": "light.shower_light",
    "44": "switch.bathroom_fan_switch",
    "45": "light.bathroom_mirror_1",
    "46": "light.bathroom_mirror_3",
    "47": "light.bathroom_mirror_4",
    "50": "scene.couch_reading",
    "51": "light.closet_light",
    "54": "light.liquor_cabinet_lights",
    "56": "script.apartment_shutdown",
    "57": "script.getting_ready",
    "62": "light.entertainment_light_1",
    "63": "light.entertainment_light_2",
    "64": "light.bathroom_mirror_2",
    "65": "light.inovelli_dimmer_level",
    "67": "light.kitchen_light_1",
    "68": "light.kitchen_light_4",
    "69": "light.kitchen_light_2",
    "70": "light.kitchen_light_3",
    "74": "light.entryway_light_2",
    "75": "light.entryway_light_1",
    "76": "script.cooking",
    "77": "light.nightstand_2"
}
